README.md
pyproject.toml
setup.cfg
setup.py
bitninja_ninjarpc.egg-info/PKG-INFO
bitninja_ninjarpc.egg-info/SOURCES.txt
bitninja_ninjarpc.egg-info/dependency_links.txt
bitninja_ninjarpc.egg-info/requires.txt
bitninja_ninjarpc.egg-info/top_level.txt
ninjarpc/CallHandler.py
ninjarpc/Client.py
ninjarpc/RemoteCommand.py
ninjarpc/Server.py
ninjarpc/__init__.py
ninjarpc/Encoders/JsonEncoder.py
ninjarpc/Encoders/__init__.py
ninjarpc/Exceptions/CallTimeoutException.py
ninjarpc/Exceptions/__init__.py
ninjarpc/Helpers/__init__.py
ninjarpc/Helpers/microtime.py
ninjarpc/Helpers/reconnect.py
ninjarpc/QueueManagers/QueueManagerInterface.py
ninjarpc/QueueManagers/RabbitMQ.py
ninjarpc/QueueManagers/__init__.py
ninjarpc/Routers/SimpleRouter.py
ninjarpc/Routers/__init__.py