Metadata-Version: 2.1
Name: bitninja-ninjarpc
Version: 1.1.0
Summary: RabbitMQ RPC server and client by BitNinja.io
Home-page: https://bitbucket.org/bitninjaio/bn-ninjarpc.py
Author: BitNinja.io
License: UNKNOWN
Keywords: bitninja,ninjarpc,rpc,rabbitmq
Platform: UNKNOWN
Classifier: Programming Language :: Python :: 3
Classifier: License :: OSI Approved :: MIT License
Classifier: Operating System :: OS Independent
Classifier: Intended Audience :: Developers
Classifier: Development Status :: 4 - Beta
Requires-Python: >=3.6
